LICENSE
MANIFEST.in
README.md
requirements.txt
setup.py
bin/ffwd-send
ffwd/__init__.py
ffwd/client.py
ffwd/ffwd_send.py
ffwd/samples.py
ffwd.egg-info/PKG-INFO
ffwd.egg-info/SOURCES.txt
ffwd.egg-info/dependency_links.txt
ffwd.egg-info/pbr.json
ffwd.egg-info/top_level.txt