Metadata-Version: 1.0
Name: ffwd
Version: 0.0.2
Summary: A Python client for FFWD
Home-page: UNKNOWN
Author: ['John-John Tedro']
Author-email: ['udoprog@tedro.se']
License: Apache 2.0
Platform: UNKNOWN
